{"v":4,"entries":{"configure-your-project--docs":{"id":"configure-your-project--docs","title":"Configure your project","name":"Docs","importPath":"./src/stories/Configure.mdx","storiesImports":[],"type":"docs","tags":["unattached-mdx","docs"]},"atom-brandedselectbutton--docs":{"id":"atom-brandedselectbutton--docs","title":"atom/BrandedSelectButton","name":"Docs","importPath":"./src/stories/BrandedSelectButton.stories.ts","type":"docs","tags":["autodocs","docs"],"storiesImports":[]},"atom-brandedselectbutton--default":{"id":"atom-brandedselectbutton--default","title":"atom/BrandedSelectButton","name":"Default","importPath":"./src/stories/BrandedSelectButton.stories.ts","tags":["autodocs","story"],"type":"story"},"atom-brandedselectbutton--active":{"id":"atom-brandedselectbutton--active","title":"atom/BrandedSelectButton","name":"Active","importPath":"./src/stories/BrandedSelectButton.stories.ts","tags":["autodocs","story"],"type":"story"},"atom-button--docs":{"id":"atom-button--docs","title":"atom/Button","name":"Docs","importPath":"./src/stories/Button.stories.ts","type":"docs","tags":["autodocs","docs"],"storiesImports":[]},"atom-button--small":{"id":"atom-button--small","title":"atom/Button","name":"Small","importPath":"./src/stories/Button.stories.ts","tags":["autodocs","story"],"type":"story"},"atom-button--medium":{"id":"atom-button--medium","title":"atom/Button","name":"Medium","importPath":"./src/stories/Button.stories.ts","tags":["autodocs","story"],"type":"story"},"atom-button--large":{"id":"atom-button--large","title":"atom/Button","name":"Large","importPath":"./src/stories/Button.stories.ts","tags":["autodocs","story"],"type":"story"},"atom-button--x-large":{"id":"atom-button--x-large","title":"atom/Button","name":"X Large","importPath":"./src/stories/Button.stories.ts","tags":["autodocs","story"],"type":"story"},"atom-button--customized-button":{"id":"atom-button--customized-button","title":"atom/Button","name":"Customized Button","importPath":"./src/stories/Button.stories.ts","tags":["autodocs","story"],"type":"story"},"atom-headerbutton--docs":{"id":"atom-headerbutton--docs","title":"atom/HeaderButton","name":"Docs","importPath":"./src/stories/HeaderButton.stories.ts","type":"docs","tags":["autodocs","docs"],"storiesImports":[]},"atom-headerbutton--inactive":{"id":"atom-headerbutton--inactive","title":"atom/HeaderButton","name":"Inactive","importPath":"./src/stories/HeaderButton.stories.ts","tags":["autodocs","story"],"type":"story"},"atom-headerbutton--active":{"id":"atom-headerbutton--active","title":"atom/HeaderButton","name":"Active","importPath":"./src/stories/HeaderButton.stories.ts","tags":["autodocs","story"],"type":"story"},"atom-headerbutton--active-custom-color":{"id":"atom-headerbutton--active-custom-color","title":"atom/HeaderButton","name":"Active Custom Color","importPath":"./src/stories/HeaderButton.stories.ts","tags":["autodocs","story"],"type":"story"},"atom-multiselect--docs":{"id":"atom-multiselect--docs","title":"atom/Multiselect","name":"Docs","importPath":"./src/stories/Multiselect.stories.ts","type":"docs","tags":["autodocs","docs"],"storiesImports":[]},"atom-multiselect--default":{"id":"atom-multiselect--default","title":"atom/Multiselect","name":"Default","importPath":"./src/stories/Multiselect.stories.ts","tags":["autodocs","story"],"type":"story"},"atom-radioinput--docs":{"id":"atom-radioinput--docs","title":"atom/RadioInput","name":"Docs","importPath":"./src/stories/RadioInput.stories.ts","type":"docs","tags":["autodocs","docs"],"storiesImports":[]},"atom-radioinput--default":{"id":"atom-radioinput--default","title":"atom/RadioInput","name":"Default","importPath":"./src/stories/RadioInput.stories.ts","tags":["autodocs","story"],"type":"story"},"atom-textinput--docs":{"id":"atom-textinput--docs","title":"atom/TextInput","name":"Docs","importPath":"./src/stories/TextInput.stories.ts","type":"docs","tags":["autodocs","docs"],"storiesImports":[]},"atom-textinput--default":{"id":"atom-textinput--default","title":"atom/TextInput","name":"Default","importPath":"./src/stories/TextInput.stories.ts","tags":["autodocs","story"],"type":"story"},"atom-textinput--with-placeholder":{"id":"atom-textinput--with-placeholder","title":"atom/TextInput","name":"With Placeholder","importPath":"./src/stories/TextInput.stories.ts","tags":["autodocs","story"],"type":"story"},"atom-textinput--error":{"id":"atom-textinput--error","title":"atom/TextInput","name":"Error","importPath":"./src/stories/TextInput.stories.ts","tags":["autodocs","story"],"type":"story"},"atom-yearlytable--docs":{"id":"atom-yearlytable--docs","title":"atom/YearlyTable","name":"Docs","importPath":"./src/stories/YearlyTable.stories.ts","type":"docs","tags":["autodocs","docs"],"storiesImports":[]},"atom-yearlytable--default":{"id":"atom-yearlytable--default","title":"atom/YearlyTable","name":"Default","importPath":"./src/stories/YearlyTable.stories.ts","tags":["autodocs","story"],"type":"story"}}}
